mdsnake/__init__.py
mdsnake/convert.py
mdsnake/dialog.py
mdsnake/localhost.py
mdsnake/main.py
mdsnake/templates.py
mdsnake-0.4.4.dist-info/licenses/LICENSE
mdsnake-0.4.4.dist-info/METADATA
mdsnake-0.4.4.dist-info/WHEEL
mdsnake-0.4.4.dist-info/entry_points.txt
mdsnake-0.4.4.dist-info/top_level.txt
mdsnake-0.4.4.dist-info/RECORD
